LICENSE
MANIFEST.in
README.md
pyproject.toml
setup.py
src/pathsig/Signature.py
src/pathsig/__init__.py
src/pathsig/_autograd.py
src/pathsig/pybindings.cpp
src/pathsig.egg-info/PKG-INFO
src/pathsig.egg-info/SOURCES.txt
src/pathsig.egg-info/dependency_links.txt
src/pathsig.egg-info/not-zip-safe
src/pathsig.egg-info/top_level.txt
src/pathsig/signature_backward/sig_backprop.cu
src/pathsig/signature_backward/sig_backprop.cuh
src/pathsig/signature_backward/sig_backprop_launch.cu
src/pathsig/signature_backward/sig_backprop_launch.cuh
src/pathsig/signature_forward/compute_sig.cu
src/pathsig/signature_forward/compute_sig.cuh
src/pathsig/signature_forward/compute_sig_launch.cu
src/pathsig/signature_forward/compute_sig_launch.cuh
src/pathsig/utils/SigDecomposition.cpp
src/pathsig/utils/SigDecomposition.h
src/pathsig/utils/extended_precision.cuh
src/pathsig/utils/sig_setup.cu
src/pathsig/utils/sig_setup.cuh
src/pathsig/utils/word_mappings.cuh
tests/test_forward_backward.py