Metadata-Version: 2.4
Name: pathsig
Version: 0.1.1
Summary: GPU-accelerated library for scalable and efficient differentiable signature computations.
Author-email: Tobias Nygaard <tobiasknygard@gmail.com>
Project-URL: Homepage, https://github.com/tobiasny12/pathsig
Requires-Python: >=3.8
License-File: LICENSE
Dynamic: license-file
